pyscaps/__init__.py
pyscaps/_version.py
pyscaps/common.py
pyscaps/eb.py
pyscaps/gen.py
pyscaps/gnr.py
pyscaps/iv.py
pyscaps/model.py
pyscaps-0.0.1.post1.dist-info/LICENSE
pyscaps-0.0.1.post1.dist-info/METADATA
pyscaps-0.0.1.post1.dist-info/WHEEL
pyscaps-0.0.1.post1.dist-info/top_level.txt
pyscaps-0.0.1.post1.dist-info/RECORD
