Metadata-Version: 2.1
Name: pyscaps
Version: 0.0.1.post1
Summary: Library for analyzing SCAPS-1D models and results.
Home-page: UNKNOWN
Author: Brian Carlsen
Author-email: carlsen.bri@gmail.com
License: UNKNOWN
Project-URL: Source Code, https://github.com/bicarlsen/pyscaps
Project-URL: Bug Tracker, https://github.com/bicarlsen/pyscaps/issues
Keywords: scaps,scaps-1d
Platform: UNKNOWN
Classifier: Programming Language :: Python :: 3
Classifier: License :: OSI Approved :: GNU General Public License v3 (GPLv3)
Classifier: Operating System :: Microsoft :: Windows
Classifier: Development Status :: 3 - Alpha
Requires-Python: >=3.7
License-File: LICENSE
Requires-Dist: bric-analysis-libraries (>=0.1.1)
Requires-Dist: numpy (>=1.22)
Requires-Dist: pandas (>=1.4)
